gnrt/__init__.py
gnrt/gnrt.py
gnrt-0.3.0.dist-info/LICENSE
gnrt-0.3.0.dist-info/METADATA
gnrt-0.3.0.dist-info/WHEEL
gnrt-0.3.0.dist-info/entry_points.txt
gnrt-0.3.0.dist-info/top_level.txt
gnrt-0.3.0.dist-info/RECORD
