Metadata-Version: 2.1
Name: gnrt
Version: 0.3.0
Summary: A fast and lightweight static site generator
Home-page: https://github.com/jfhovinne/gnrt
Author: jfhovinne
Author-email: gnrt@hovinne.com
License: MIT
Platform: UNKNOWN
Classifier: Programming Language :: Python :: 3
Classifier: License :: OSI Approved :: MIT License
Classifier: Operating System :: OS Independent
Classifier: Topic :: Internet :: WWW/HTTP
Requires-Python: >=3.6
License-File: LICENSE
Requires-Dist: jinja2
Requires-Dist: markdown2
Requires-Dist: python-frontmatter
Requires-Dist: pyyaml
